final_code_203/__init__.py
final_code_203/backtest.py
final_code_203/forward_broker.py
final_code_203/launch.py
final_code_203/main.py
final_code_203/predict_spot.py
python_203-main/__init__.py
python_203-main/backtest.py
python_203-main/forward_broker.py
python_203-main/launch.py
python_203-main/main.py
python_203-main/predict_spot.py
python_203-main/python_203-main.py
final_code_203-0.1.dist-info/METADATA
final_code_203-0.1.dist-info/WHEEL
final_code_203-0.1.dist-info/top_level.txt
final_code_203-0.1.dist-info/RECORD
