Metadata-Version: 2.2
Name: final_code_203
Version: 0.1
Requires-Dist: absl-py>=2.1.0
Requires-Dist: ace_tools>=0.0
Requires-Dist: adagio==0.2.6
Requires-Dist: aiohappyeyeballs==2.4.4
Requires-Dist: aiohttp==3.11.11
Requires-Dist: aiosignal==1.3.2
Requires-Dist: altair==5.5.0
Requires-Dist: anyio==4.7.0
Requires-Dist: appdirs==1.4.4
Requires-Dist: arch==7.2.0
Requires-Dist: argon2-cffi==23.1.0
Requires-Dist: argon2-cffi-bindings==21.2.0
Requires-Dist: arrow==1.3.0
Requires-Dist: asttokens==2.4.1
Requires-Dist: astunparse==1.6.3
Requires-Dist: async-lru==2.0.4
Requires-Dist: attrs==24.3.0
Requires-Dist: babel==2.16.0
Requires-Dist: beautifulsoup4==4.12.3
Requires-Dist: bleach==6.2.0
Requires-Dist: blinker==1.9.0
Requires-Dist: build==1.2.1
Requires-Dist: CacheControl==0.14.0
Requires-Dist: cachetools==5.5.0
Requires-Dist: certifi==2024.2.2
Requires-Dist: cffi==1.17.1
Requires-Dist: charset-normalizer==3.3.2
Requires-Dist: cleo==2.1.0
Requires-Dist: click==8.1.8
Requires-Dist: cloudpickle==3.1.0
Requires-Dist: colorama==0.4.6
Requires-Dist: comm==0.2.2
Requires-Dist: contourpy==1.1.1
Requires-Dist: coreforecast==0.0.15
Requires-Dist: crashtest==0.4.1
Requires-Dist: cycler==0.12.1
Requires-Dist: Cython==3.0.10
Requires-Dist: darts==0.32.0
Requires-Dist: DatastreamPy==2.0.21
Requires-Dist: dbnomics==1.2.5
Requires-Dist: debugpy==1.8.1
Requires-Dist: decorator==5.1.1
Requires-Dist: defusedxml==0.7.1
Requires-Dist: distlib==0.3.8
Requires-Dist: dulwich==0.21.7
Requires-Dist: et-xmlfile==1.1.0
Requires-Dist: executing==2.0.1
Requires-Dist: fastjsonschema==2.20.0
Requires-Dist: filelock==3.15.4
Requires-Dist: flatbuffers==24.12.23
Requires-Dist: fonttools==4.43.1
Requires-Dist: forex-python==1.8
Requires-Dist: formulaic==1.0.1
Requires-Dist: fqdn==1.5.1
Requires-Dist: frozendict==2.4.2
Requires-Dist: frozenlist==1.5.0
Requires-Dist: fs==2.4.16
Requires-Dist: fsspec==2024.12.0
Requires-Dist: fugue==0.9.1
Requires-Dist: gast==0.6.0
Requires-Dist: gitdb==4.0.12
Requires-Dist: GitPython==3.1.44
Requires-Dist: google-pasta==0.2.0
Requires-Dist: grpcio==1.68.1
Requires-Dist: h11==0.14.0
Requires-Dist: h5py==3.12.1
Requires-Dist: holidays==0.63
Requires-Dist: html5lib==1.1
Requires-Dist: httpcore==1.0.7
Requires-Dist: httpx==0.28.1
Requires-Dist: idna==3.6
Requires-Dist: importlib_metadata==8.4.0
Requires-Dist: inflection==0.5.1
Requires-Dist: installer==0.7.0
Requires-Dist: interface-meta==1.3.0
Requires-Dist: investpy==1.0.8
Requires-Dist: ipykernel==6.29.4
Requires-Dist: ipython==8.25.0
Requires-Dist: ipywidgets==8.1.5
Requires-Dist: isoduration==20.11.0
Requires-Dist: jaraco.classes==3.4.0
Requires-Dist: jedi==0.19.1
Requires-Dist: Jinja2==3.1.5
Requires-Dist: joblib==1.3.2
Requires-Dist: json5==0.10.0
Requires-Dist: jsonpointer==3.0.0
Requires-Dist: jsonschema==4.23.0
Requires-Dist: jsonschema-specifications==2024.10.1
Requires-Dist: jupyter==1.1.1
Requires-Dist: jupyter-console==6.6.3
Requires-Dist: jupyter-events==0.11.0
Requires-Dist: jupyter-lsp==2.2.5
Requires-Dist: jupyter_client==8.6.2
Requires-Dist: jupyter_core==5.7.2
Requires-Dist: jupyter_server==2.15.0
Requires-Dist: jupyter_server_terminals==0.5.3
Requires-Dist: jupyterlab==4.3.4
Requires-Dist: jupyterlab_pygments==0.3.0
Requires-Dist: jupyterlab_server==2.27.3
Requires-Dist: jupyterlab_widgets==3.0.13
Requires-Dist: keras==3.7.0
Requires-Dist: keyring==24.3.1
Requires-Dist: kiwisolver==1.4.5
Requires-Dist: libclang==18.1.1
Requires-Dist: lightgbm==4.5.0
Requires-Dist: lightning-utilities==0.11.9
Requires-Dist: linearmodels==6.0
Requires-Dist: llvmlite==0.43.0
Requires-Dist: lxml==5.2.1
Requires-Dist: Markdown==3.7
Requires-Dist: markdown-it-py==3.0.0
Requires-Dist: MarkupSafe==3.0.2
Requires-Dist: matplotlib==3.8.0
Requires-Dist: matplotlib-inline==0.1.7
Requires-Dist: mdurl==0.1.2
Requires-Dist: mistune==3.0.2
Requires-Dist: ml-dtypes==0.4.1
Requires-Dist: more-itertools==10.2.0
Requires-Dist: mpmath==1.3.0
Requires-Dist: msgpack==1.0.8
Requires-Dist: multidict==6.1.0
Requires-Dist: multitasking==0.0.11
Requires-Dist: mypy-extensions==1.0.0
Requires-Dist: namex==0.0.8
Requires-Dist: narwhals==1.21.1
Requires-Dist: natsort==8.2.0
Dynamic: description
Dynamic: description-content-type
Dynamic: requires-dist
